{
    "watching": [
    {"date":"Mar 2025","link":"https://en.wikipedia.org/wiki/Severance_(TV_series)","media":"Apple TV+","rating":"*****","title":"Severance, Season 2"},
    {"date":"Mar 2025","link":"https://en.wikipedia.org/wiki/Union_of_Salvation_(film)","media":"YouTube","rating":"****","title":"Union of Salvation"},
    {"date":"Mar 2025","link":"https://en.wikipedia.org/wiki/War_%26_Peace_(2016_TV_series)","media":"Prime Video","rating":"***","title":"War & Peace"},
    {"date":"Feb 2025","link":"https://en.wikipedia.org/wiki/Fillmore!","media":"DVD","rating":"****","title":"Filmore! Season 1"}
    ]
}